vptrade/__init__.py
vptrade/base.py
vptrade/version.py
vptrade/indicators/__init__.py
vptrade/indicators/oscillators.py
vptrade/indicators/trends.py
vptrade/plots/__init__.py
vptrade/plots/visualize.py
vptrade/strategies/__init__.py
vptrade/strategies/moving_average.py
vptrade-0.0.2.dist-info/LICENSE
vptrade-0.0.2.dist-info/METADATA
vptrade-0.0.2.dist-info/WHEEL
vptrade-0.0.2.dist-info/top_level.txt
vptrade-0.0.2.dist-info/RECORD
