Metadata-Version: 2.1
Name: vptrade
Version: 0.0.2
Summary: vptrade is a technical indicators trading tools can be used to all instruments.
Home-page: https://github.com/vnpnh/vptrade
Author: vnpnh
Author-email: no@email.com
License: MIT
Keywords: technical analysis,ta,trading tools,finance,trading,analysis
Platform: UNKNOWN
Classifier: License :: OSI Approved :: MIT License
Classifier: Operating System :: OS Independent
Classifier: Programming Language :: Python :: 3
Classifier: Programming Language :: Python :: 3.9
Classifier: Programming Language :: Python :: 3.10
License-File: LICENSE
Requires-Dist: matplotlib
Requires-Dist: pandas
Requires-Dist: numpy
